{"doc_java_java-thread.md":"CoAjmT-Y","doc_db_castled.md":"jdfYv6il","doc_db_oceanbase.md":"QP2sV8qw","doc_db_clickhouse.md":"Dv32Ql_-","doc_java_logback.md":"BoFfHVwo","doc_java_java-constant.md":"8xhTxbxK","doc_db_sqlserver.md":"DhTehnzh","doc_db_questdb.md":"C7oS7oy3","doc_db_dremio.md":"_KHT8-qK","doc_java_json.md":"CBD6VjMR","doc_db_duckdb.md":"BxpEqMfF","doc_db_trino.md":"BrkgNuww","doc_db_index.md":"DTgki9s0","doc_java_poi.md":"DV1ECE9P","doc_java_java-io.md":"DMEfD2dh","doc_db_redis.md":"B4IRqvfb","doc_js_index.md":"B2fO7Z3Z","doc_java_shardingjdbc.md":"BjK3nx_o","doc_db_neo4j.md":"Uw3QSA6z","doc_js_原生js.md":"C_s7pj-d","doc_ops_bruno.md":"CmPajURb","doc_java_jackson.md":"CFx_Q2z6","doc_db_mysql.md":"Nz8nHKib","doc_ops_docker-常用指令.md":"BtYFli84","doc_java_resttemplate.md":"jWkaTHJk","doc_practice_阿里云运维实践.md":"-gwfspUH","doc_ops_nginx.md":"DC2XSMRM","doc_java_springboot基础.md":"B3ddf0h3","doc_java_jdbctemplate.md":"Bc_qCN1V","doc_java_guava.md":"C2de47UX","doc_js_cube.js.md":"NT3JsUHj","doc_db_oracle.md":"oQzbS-Iz","doc_java_java-stream.md":"mCN_nCJI","doc_java_java-lamdba.md":"Dcajnl6l","doc_db_greenplum.md":"BIW5PXEG","doc_java_springboot进阶.md":"CVevEX7y","doc_ops_minio.md":"g-0TZbtd","doc_java_java-utils.md":"BYTo3YM3","doc_js_cubejs-sql.md":"BvEVao-6","doc_java_okhttp3.md":"DMSf1_OK","doc_js_docsify.js.md":"C8h4Z-Cp","doc_js_jquery.js.md":"BPaNS8Kc","doc_ops_nacos.md":"Y16zb0DT","doc_ops_gitlab.md":"B60j3duR","doc_js_readme.md":"Bp8WpSZk","doc_ops_graylog.md":"CAWZhpiN","doc_ops_jprofiler.md":"CZY2zwh5","doc_ops_idea.md":"BLaYzerH","doc_db_flink.md":"C5bON_z2","doc_ops_jmeter_k6.md":"BidH3Qx1","doc_ops_k8s.md":"B0Ty2y_l","doc_ops_index.md":"DY3YCWg3","doc_ops_rabbitmq.md":"-npnZIKt","doc_ops_srs.md":"CzamVVJ5","doc_ops_docker-异常排查.md":"Blnid2OZ","index.md":"pErm8F4o","doc_ops_docker-安装.md":"DbR48Ro3","doc_practice_贫血模型_充血模型.md":"MDfbdHL9","doc_practice_设计模式.md":"DONDUH-u","doc_practice_gitlab_jenkins_docker实践.md":"C0FHSLu2","doc_practice_index.md":"ClPYMwoC","doc_practice_开发安全实践.md":"DuASP1P9","doc_practice_反向etl.md":"DayzSLJp","doc_db_s3.md":"BysJBqpD","doc_practice_设计与思考.md":"CXHbksMt","doc_practice_插件式接口开发.md":"DjuNhMUl","doc_practice_项目实战-字典管理.md":"BNBuP9iv","doc_ops_docker-常用镜像.md":"GirHEnOJ","doc_java_安全框架.md":"BGSJDAVu","doc_java_index.md":"ByS_gF71","doc_ops_caddy.md":"e4n_ZEi7","doc_java_hazelcast.md":"AfDlmonu","doc_ops_debezium.md":"DRixoGQF","doc_practice_http编排调度实践.md":"EpOLMl0Z","doc_java_openfeign.md":"DRIZlQWx","doc_ops_cmd.md":"CkbXqgKq","doc_java_java-reflect-generic.md":"D5J9nH8U","doc_ops_网络工具.md":"C3ASovkE","doc_db_kafka.md":"B9jJQXNT","doc_ops_阿里云部署.md":"BZabXqIx","doc_java_java-serializable.md":"B3qYbkxo","doc_java_spring基础.md":"BsBa4qr_","doc_ops_feed.md":"DdB-M-Il","doc_ops_centraldogma.md":"D_o4ACHk","doc_ops_maven.md":"CftK9-Ul","doc_java_springcloud.md":"BVm14qqq"}
